<?x0ml v0ersion="1.0" ?>
<Gesture Subject="6" Name="right_square_bracket03" Number="3" NumPts="81" Date="28-02-2023" Time="16:12:11">
	<Point X="464" Y="288" T="2"/>
	<Point X="472" Y="290" T="3"/>
	<Point X="477" Y="291" T="4"/>
	<Point X="483" Y="292" T="5"/>
	<Point X="491" Y="293" T="6"/>
	<Point X="501" Y="294" T="7"/>
	<Point X="509" Y="295" T="8"/>
	<Point X="516" Y="296" T="9"/>
	<Point X="520" Y="296" T="10"/>
	<Point X="523" Y="297" T="11"/>
	<Point X="525" Y="297" T="12"/>
	<Point X="527" Y="297" T="13"/>
	<Point X="528" Y="297" T="14"/>
	<Point X="529" Y="297" T="15"/>
	<Point X="530" Y="298" T="16"/>
	<Point X="531" Y="298" T="17"/>
	<Point X="531" Y="298" T="18"/>
	<Point X="531" Y="299" T="19"/>
	<Point X="531" Y="299" T="20"/>
	<Point X="531" Y="301" T="21"/>
	<Point X="531" Y="303" T="22"/>
	<Point X="531" Y="307" T="23"/>
	<Point X="531" Y="312" T="24"/>
	<Point X="531" Y="317" T="25"/>
	<Point X="532" Y="322" T="26"/>
	<Point X="532" Y="328" T="27"/>
	<Point X="531" Y="333" T="28"/>
	<Point X="529" Y="342" T="29"/>
	<Point X="528" Y="350" T="30"/>
	<Point X="527" Y="359" T="31"/>
	<Point X="527" Y="364" T="32"/>
	<Point X="526" Y="370" T="33"/>
	<Point X="526" Y="375" T="34"/>
	<Point X="526" Y="381" T="35"/>
	<Point X="526" Y="387" T="36"/>
	<Point X="526" Y="394" T="37"/>
	<Point X="526" Y="398" T="38"/>
	<Point X="526" Y="404" T="39"/>
	<Point X="526" Y="408" T="40"/>
	<Point X="527" Y="413" T="41"/>
	<Point X="528" Y="418" T="42"/>
	<Point X="529" Y="423" T="43"/>
	<Point X="530" Y="428" T="44"/>
	<Point X="531" Y="434" T="45"/>
	<Point X="531" Y="438" T="46"/>
	<Point X="531" Y="441" T="47"/>
	<Point X="531" Y="445" T="48"/>
	<Point X="531" Y="447" T="49"/>
	<Point X="531" Y="448" T="50"/>
	<Point X="531" Y="449" T="51"/>
	<Point X="531" Y="450" T="52"/>
	<Point X="531" Y="451" T="53"/>
	<Point X="531" Y="452" T="54"/>
	<Point X="531" Y="452" T="55"/>
	<Point X="531" Y="453" T="56"/>
	<Point X="531" Y="454" T="57"/>
	<Point X="531" Y="455" T="58"/>
	<Point X="531" Y="455" T="59"/>
	<Point X="530" Y="455" T="60"/>
	<Point X="525" Y="455" T="61"/>
	<Point X="519" Y="457" T="62"/>
	<Point X="516" Y="457" T="63"/>
	<Point X="509" Y="459" T="64"/>
	<Point X="504" Y="460" T="65"/>
	<Point X="502" Y="460" T="66"/>
	<Point X="497" Y="462" T="67"/>
	<Point X="491" Y="463" T="68"/>
	<Point X="486" Y="465" T="69"/>
	<Point X="480" Y="465" T="70"/>
	<Point X="474" Y="466" T="71"/>
	<Point X="471" Y="467" T="72"/>
	<Point X="468" Y="467" T="73"/>
	<Point X="464" Y="468" T="74"/>
	<Point X="462" Y="468" T="75"/>
	<Point X="459" Y="468" T="76"/>
	<Point X="457" Y="468" T="77"/>
	<Point X="455" Y="469" T="78"/>
	<Point X="454" Y="469" T="79"/>
	<Point X="453" Y="469" T="80"/>
	<Point X="452" Y="469" T="81"/>
	<Point X="451" Y="469" T="82"/>
</Gesture>
