<?xml version="1.0" ?>
<Gesture User="user6" Gesture="rectangle5" Number="5" NumPts="216" Date="28-02-2023" Time="16:12:11">
	<Point X="409" Y="325"/>
	<Point X="409" Y="332"/>
	<Point X="408" Y="337"/>
	<Point X="407" Y="345"/>
	<Point X="407" Y="351"/>
	<Point X="406" Y="359"/>
	<Point X="405" Y="367"/>
	<Point X="404" Y="375"/>
	<Point X="403" Y="381"/>
	<Point X="403" Y="389"/>
	<Point X="402" Y="395"/>
	<Point X="401" Y="400"/>
	<Point X="400" Y="406"/>
	<Point X="400" Y="412"/>
	<Point X="399" Y="416"/>
	<Point X="399" Y="421"/>
	<Point X="398" Y="424"/>
	<Point X="398" Y="427"/>
	<Point X="398" Y="430"/>
	<Point X="398" Y="432"/>
	<Point X="398" Y="435"/>
	<Point X="398" Y="438"/>
	<Point X="398" Y="441"/>
	<Point X="398" Y="444"/>
	<Point X="398" Y="447"/>
	<Point X="398" Y="450"/>
	<Point X="398" Y="453"/>
	<Point X="398" Y="456"/>
	<Point X="398" Y="458"/>
	<Point X="398" Y="460"/>
	<Point X="398" Y="461"/>
	<Point X="398" Y="462"/>
	<Point X="398" Y="463"/>
	<Point X="398" Y="465"/>
	<Point X="398" Y="466"/>
	<Point X="398" Y="467"/>
	<Point X="398" Y="468"/>
	<Point X="398" Y="469"/>
	<Point X="398" Y="470"/>
	<Point X="398" Y="471"/>
	<Point X="398" Y="472"/>
	<Point X="398" Y="473"/>
	<Point X="398" Y="474"/>
	<Point X="398" Y="475"/>
	<Point X="398" Y="476"/>
	<Point X="398" Y="476"/>
	<Point X="398" Y="477"/>
	<Point X="400" Y="477"/>
	<Point X="405" Y="477"/>
	<Point X="411" Y="478"/>
	<Point X="418" Y="478"/>
	<Point X="425" Y="478"/>
	<Point X="432" Y="477"/>
	<Point X="439" Y="476"/>
	<Point X="448" Y="476"/>
	<Point X="456" Y="475"/>
	<Point X="465" Y="475"/>
	<Point X="473" Y="475"/>
	<Point X="481" Y="475"/>
	<Point X="490" Y="475"/>
	<Point X="498" Y="475"/>
	<Point X="507" Y="476"/>
	<Point X="514" Y="476"/>
	<Point X="522" Y="476"/>
	<Point X="528" Y="476"/>
	<Point X="536" Y="476"/>
	<Point X="543" Y="476"/>
	<Point X="548" Y="476"/>
	<Point X="555" Y="476"/>
	<Point X="560" Y="476"/>
	<Point X="565" Y="476"/>
	<Point X="570" Y="475"/>
	<Point X="574" Y="474"/>
	<Point X="579" Y="473"/>
	<Point X="583" Y="473"/>
	<Point X="587" Y="472"/>
	<Point X="590" Y="471"/>
	<Point X="594" Y="471"/>
	<Point X="597" Y="471"/>
	<Point X="599" Y="470"/>
	<Point X="602" Y="470"/>
	<Point X="604" Y="470"/>
	<Point X="605" Y="469"/>
	<Point X="607" Y="469"/>
	<Point X="609" Y="469"/>
	<Point X="610" Y="469"/>
	<Point X="612" Y="469"/>
	<Point X="613" Y="469"/>
	<Point X="614" Y="469"/>
	<Point X="615" Y="469"/>
	<Point X="616" Y="469"/>
	<Point X="617" Y="469"/>
	<Point X="618" Y="469"/>
	<Point X="619" Y="469"/>
	<Point X="620" Y="469"/>
	<Point X="620" Y="469"/>
	<Point X="621" Y="469"/>
	<Point X="622" Y="469"/>
	<Point X="623" Y="469"/>
	<Point X="624" Y="469"/>
	<Point X="625" Y="469"/>
	<Point X="626" Y="469"/>
	<Point X="627" Y="469"/>
	<Point X="628" Y="468"/>
	<Point X="630" Y="464"/>
	<Point X="630" Y="460"/>
	<Point X="630" Y="455"/>
	<Point X="630" Y="448"/>
	<Point X="630" Y="441"/>
	<Point X="630" Y="434"/>
	<Point X="630" Y="428"/>
	<Point X="630" Y="422"/>
	<Point X="630" Y="415"/>
	<Point X="630" Y="409"/>
	<Point X="630" Y="402"/>
	<Point X="630" Y="395"/>
	<Point X="630" Y="388"/>
	<Point X="630" Y="381"/>
	<Point X="630" Y="375"/>
	<Point X="630" Y="369"/>
	<Point X="630" Y="364"/>
	<Point X="630" Y="359"/>
	<Point X="630" Y="354"/>
	<Point X="630" Y="351"/>
	<Point X="630" Y="348"/>
	<Point X="630" Y="345"/>
	<Point X="630" Y="343"/>
	<Point X="630" Y="341"/>
	<Point X="630" Y="339"/>
	<Point X="630" Y="337"/>
	<Point X="630" Y="335"/>
	<Point X="630" Y="333"/>
	<Point X="630" Y="332"/>
	<Point X="630" Y="331"/>
	<Point X="630" Y="328"/>
	<Point X="630" Y="326"/>
	<Point X="630" Y="325"/>
	<Point X="629" Y="323"/>
	<Point X="629" Y="322"/>
	<Point X="629" Y="321"/>
	<Point X="629" Y="320"/>
	<Point X="629" Y="319"/>
	<Point X="628" Y="318"/>
	<Point X="628" Y="317"/>
	<Point X="628" Y="316"/>
	<Point X="628" Y="315"/>
	<Point X="628" Y="314"/>
	<Point X="628" Y="313"/>
	<Point X="628" Y="312"/>
	<Point X="627" Y="312"/>
	<Point X="626" Y="312"/>
	<Point X="625" Y="312"/>
	<Point X="624" Y="312"/>
	<Point X="623" Y="312"/>
	<Point X="621" Y="312"/>
	<Point X="618" Y="312"/>
	<Point X="615" Y="312"/>
	<Point X="610" Y="312"/>
	<Point X="604" Y="312"/>
	<Point X="599" Y="312"/>
	<Point X="592" Y="310"/>
	<Point X="587" Y="310"/>
	<Point X="581" Y="311"/>
	<Point X="576" Y="311"/>
	<Point X="571" Y="312"/>
	<Point X="567" Y="312"/>
	<Point X="561" Y="312"/>
	<Point X="555" Y="313"/>
	<Point X="550" Y="313"/>
	<Point X="544" Y="313"/>
	<Point X="539" Y="313"/>
	<Point X="533" Y="313"/>
	<Point X="527" Y="313"/>
	<Point X="523" Y="313"/>
	<Point X="517" Y="313"/>
	<Point X="511" Y="313"/>
	<Point X="507" Y="313"/>
	<Point X="501" Y="313"/>
	<Point X="496" Y="313"/>
	<Point X="491" Y="314"/>
	<Point X="487" Y="314"/>
	<Point X="483" Y="314"/>
	<Point X="479" Y="314"/>
	<Point X="475" Y="315"/>
	<Point X="471" Y="315"/>
	<Point X="466" Y="316"/>
	<Point X="463" Y="316"/>
	<Point X="458" Y="316"/>
	<Point X="452" Y="317"/>
	<Point X="449" Y="317"/>
	<Point X="446" Y="317"/>
	<Point X="443" Y="317"/>
	<Point X="440" Y="317"/>
	<Point X="438" Y="317"/>
	<Point X="436" Y="317"/>
	<Point X="434" Y="317"/>
	<Point X="433" Y="317"/>
	<Point X="432" Y="317"/>
	<Point X="430" Y="317"/>
	<Point X="429" Y="317"/>
	<Point X="428" Y="317"/>
	<Point X="427" Y="317"/>
	<Point X="426" Y="317"/>
	<Point X="425" Y="317"/>
	<Point X="424" Y="317"/>
	<Point X="423" Y="317"/>
	<Point X="422" Y="317"/>
	<Point X="421" Y="317"/>
	<Point X="420" Y="317"/>
	<Point X="419" Y="317"/>
	<Point X="418" Y="317"/>
	<Point X="418" Y="317"/>
	<Point X="417" Y="317"/>
	<Point X="416" Y="317"/>
	<Point X="415" Y="317"/>
	<Point X="414" Y="317"/>
</Gesture>
