{"user6": {"1": {"delete": 10, "caret": 10, "rectangle": 10, "zig_zag": 9, "triangle": 7, "right_square_bracket": 9, "pigtail": 7, "v": 10, "x": 10, "arrow": 8, "check": 10, "left_square_bracket": 10, "star": 10, "left_curly_brace": 10, "circle": 10, "right_curly_brace": 9}, "2": {"delete": 10, "caret": 10, "rectangle": 10, "zig_zag": 10, "triangle": 9, "right_square_bracket": 10, "pigtail": 9, "v": 10, "x": 10, "arrow": 10, "check": 10, "left_square_bracket": 10, "star": 10, "left_curly_brace": 10, "circle": 10, "right_curly_brace": 10}, "3": {"delete": 10, "caret": 10, "rectangle": 10, "zig_zag": 8, "triangle": 9, "right_square_bracket": 10, "pigtail": 6, "v": 10, "x": 10, "arrow": 10, "check": 10, "left_square_bracket": 10, "star": 10, "left_curly_brace": 9, "circle": 10, "right_curly_brace": 10}, "4": {"delete": 10, "caret": 10, "rectangle": 10, "zig_zag": 9, "triangle": 10, "right_square_bracket": 9, "pigtail": 8, "v": 10, "x": 10, "arrow": 10, "check": 10, "left_square_bracket": 10, "star": 10, "left_curly_brace": 10, "circle": 10, "right_curly_brace": 8}, "5": {"delete": 10, "caret": 10, "rectangle": 10, "zig_zag": 10, "triangle": 10, "right_square_bracket": 9, "pigtail": 10, "v": 10, "x": 10, "arrow": 10, "check": 10, "left_square_bracket": 10, "star": 10, "left_curly_brace": 10, "circle": 10, "right_curly_brace": 10}}, "user1": {"1": {"delete": 10, "caret": 10, "rectangle": 10, "zig_zag": 10, "triangle": 10, "right_square_bracket": 9, "pigtail": 10, "v": 9, "x": 10, "arrow": 7, "check": 10, "left_square_bracket": 10, "star": 10, "left_curly_brace": 10, "circle": 10, "right_curly_brace": 8}, "2": {"delete": 10, "caret": 10, "rectangle": 9, "zig_zag": 10, "triangle": 10, "right_square_bracket": 9, "pigtail": 10, "v": 10, "x": 10, "arrow": 9, "check": 10, "left_square_bracket": 10, "star": 10, "left_curly_brace": 9, "circle": 10, "right_curly_brace": 9}, "3": {"delete": 10, "caret": 10, "rectangle": 10, "zig_zag": 10, "triangle": 10, "right_square_bracket": 10, "pigtail": 10, "v": 10, "x": 10, "arrow": 9, "check": 10, "left_square_bracket": 10, "star": 10, "left_curly_brace": 8, "circle": 9, "right_curly_brace": 9}, "4": {"delete": 10, "caret": 10, "rectangle": 10, "zig_zag": 10, "triangle": 10, "right_square_bracket": 9, "pigtail": 10, "v": 10, "x": 10, "arrow": 9, "check": 10, "left_square_bracket": 10, "star": 10, "left_curly_brace": 10, "circle": 10, "right_curly_brace": 9}, "5": {"delete": 10, "caret": 10, "rectangle": 10, "zig_zag": 10, "triangle": 10, "right_square_bracket": 10, "pigtail": 10, "v": 10, "x": 10, "arrow": 9, "check": 10, "left_square_bracket": 10, "star": 10, "left_curly_brace": 10, "circle": 10, "right_curly_brace": 10}}, "user4": {"1": {"delete": 10, "caret": 10, "rectangle": 10, "zig_zag": 10, "triangle": 10, "right_square_bracket": 9, "pigtail": 10, "v": 10, "x": 10, "arrow": 10, "check": 10, "left_square_bracket": 10, "star": 10, "left_curly_brace": 9, "circle": 10, "right_curly_brace": 10}, "2": {"delete": 10, "caret": 10, "rectangle": 10, "zig_zag": 10, "triangle": 10, "right_square_bracket": 9, "pigtail": 10, "v": 10, "x": 10, "arrow": 10, "check": 10, "left_square_bracket": 10, "star": 10, "left_curly_brace": 10, "circle": 10, "right_curly_brace": 10}, "3": {"delete": 10, "caret": 10, "rectangle": 10, "zig_zag": 10, "triangle": 10, "right_square_bracket": 10, "pigtail": 10, "v": 10, "x": 10, "arrow": 10, "check": 10, "left_square_bracket": 10, "star": 10, "left_curly_brace": 10, "circle": 10, "right_curly_brace": 10}, "4": {"delete": 10, "caret": 10, "rectangle": 10, "zig_zag": 10, "triangle": 10, "right_square_bracket": 10, "pigtail": 10, "v": 10, "x": 10, "arrow": 10, "check": 10, "left_square_bracket": 10, "star": 10, "left_curly_brace": 9, "circle": 10, "right_curly_brace": 10}, "5": {"delete": 10, "caret": 10, "rectangle": 10, "zig_zag": 10, "triangle": 10, "right_square_bracket": 10, "pigtail": 10, "v": 10, "x": 10, "arrow": 10, "check": 10, "left_square_bracket": 10, "star": 10, "left_curly_brace": 10, "circle": 10, "right_curly_brace": 10}}, "user2": {"1": {"delete": 10, "caret": 8, "rectangle": 9, "zig_zag": 9, "triangle": 10, "right_square_bracket": 6, "pigtail": 10, "v": 8, "x": 10, "arrow": 10, "check": 9, "left_square_bracket": 9, "star": 10, "left_curly_brace": 9, "circle": 8, "right_curly_brace": 10}, "2": {"delete": 10, "caret": 10, "rectangle": 9, "zig_zag": 10, "triangle": 10, "right_square_bracket": 8, "pigtail": 10, "v": 9, "x": 10, "arrow": 10, "check": 10, "left_square_bracket": 10, "star": 10, "left_curly_brace": 9, "circle": 9, "right_curly_brace": 10}, "3": {"delete": 10, "caret": 10, "rectangle": 10, "zig_zag": 10, "triangle": 10, "right_square_bracket": 10, "pigtail": 10, "v": 9, "x": 10, "arrow": 10, "check": 10, "left_square_bracket": 10, "star": 10, "left_curly_brace": 10, "circle": 10, "right_curly_brace": 10}, "4": {"delete": 10, "caret": 10, "rectangle": 10, "zig_zag": 10, "triangle": 10, "right_square_bracket": 10, "pigtail": 10, "v": 9, "x": 10, "arrow": 10, "check": 9, "left_square_bracket": 10, "star": 10, "left_curly_brace": 9, "circle": 10, "right_curly_brace": 10}, "5": {"delete": 10, "caret": 10, "rectangle": 10, "zig_zag": 10, "triangle": 10, "right_square_bracket": 10, "pigtail": 10, "v": 7, "x": 10, "arrow": 10, "check": 8, "left_square_bracket": 10, "star": 10, "left_curly_brace": 10, "circle": 10, "right_curly_brace": 10}}, "user5": {"1": {"delete": 10, "caret": 10, "rectangle": 10, "zig_zag": 10, "triangle": 10, "right_square_bracket": 10, "pigtail": 10, "v": 10, "x": 10, "arrow": 10, "check": 10, "left_square_bracket": 10, "star": 10, "left_curly_brace": 7, "circle": 9, "right_curly_brace": 9}, "2": {"delete": 10, "caret": 10, "rectangle": 10, "zig_zag": 10, "triangle": 10, "right_square_bracket": 10, "pigtail": 10, "v": 10, "x": 10, "arrow": 10, "check": 10, "left_square_bracket": 10, "star": 10, "left_curly_brace": 10, "circle": 10, "right_curly_brace": 10}, "3": {"delete": 10, "caret": 10, "rectangle": 10, "zig_zag": 10, "triangle": 10, "right_square_bracket": 10, "pigtail": 10, "v": 10, "x": 10, "arrow": 10, "check": 10, "left_square_bracket": 10, "star": 10, "left_curly_brace": 10, "circle": 10, "right_curly_brace": 10}, "4": {"delete": 10, "caret": 10, "rectangle": 10, "zig_zag": 10, "triangle": 10, "right_square_bracket": 10, "pigtail": 10, "v": 10, "x": 10, "arrow": 10, "check": 10, "left_square_bracket": 10, "star": 10, "left_curly_brace": 10, "circle": 10, "right_curly_brace": 10}, "5": {"delete": 10, "caret": 10, "rectangle": 10, "zig_zag": 10, "triangle": 10, "right_square_bracket": 10, "pigtail": 10, "v": 10, "x": 10, "arrow": 10, "check": 10, "left_square_bracket": 10, "star": 10, "left_curly_brace": 10, "circle": 10, "right_curly_brace": 10}}, "user3": {"1": {"delete": 10, "caret": 10, "rectangle": 10, "zig_zag": 9, "triangle": 10, "right_square_bracket": 9, "pigtail": 10, "v": 9, "x": 10, "arrow": 10, "check": 10, "left_square_bracket": 9, "star": 10, "left_curly_brace": 10, "circle": 8, "right_curly_brace": 9}, "2": {"delete": 10, "caret": 10, "rectangle": 10, "zig_zag": 9, "triangle": 10, "right_square_bracket": 10, "pigtail": 10, "v": 10, "x": 10, "arrow": 9, "check": 10, "left_square_bracket": 9, "star": 10, "left_curly_brace": 10, "circle": 10, "right_curly_brace": 10}, "3": {"delete": 10, "caret": 10, "rectangle": 10, "zig_zag": 9, "triangle": 10, "right_square_bracket": 10, "pigtail": 10, "v": 10, "x": 10, "arrow": 10, "check": 10, "left_square_bracket": 10, "star": 10, "left_curly_brace": 10, "circle": 10, "right_curly_brace": 9}, "4": {"delete": 10, "caret": 10, "rectangle": 10, "zig_zag": 9, "triangle": 10, "right_square_bracket": 10, "pigtail": 10, "v": 10, "x": 10, "arrow": 10, "check": 10, "left_square_bracket": 10, "star": 10, "left_curly_brace": 10, "circle": 10, "right_curly_brace": 10}, "5": {"delete": 10, "caret": 10, "rectangle": 10, "zig_zag": 10, "triangle": 10, "right_square_bracket": 10, "pigtail": 10, "v": 10, "x": 10, "arrow": 10, "check": 10, "left_square_bracket": 10, "star": 10, "left_curly_brace": 10, "circle": 10, "right_curly_brace": 10}}}