<?xml version="1.0" ?>
<Gesture User="user3" Gesture="delete2" Number="2" NumPts="37" Date="02-03-2023" Time="13:17:07">
	<Point X="215" Y="280"/>
	<Point X="221" Y="290"/>
	<Point X="232" Y="306"/>
	<Point X="245" Y="329"/>
	<Point X="261" Y="358"/>
	<Point X="277" Y="387"/>
	<Point X="287" Y="409"/>
	<Point X="293" Y="420"/>
	<Point X="296" Y="428"/>
	<Point X="298" Y="432"/>
	<Point X="299" Y="433"/>
	<Point X="298" Y="432"/>
	<Point X="297" Y="431"/>
	<Point X="295" Y="429"/>
	<Point X="293" Y="428"/>
	<Point X="287" Y="427"/>
	<Point X="275" Y="426"/>
	<Point X="254" Y="425"/>
	<Point X="236" Y="425"/>
	<Point X="224" Y="425"/>
	<Point X="213" Y="425"/>
	<Point X="208" Y="425"/>
	<Point X="207" Y="425"/>
	<Point X="206" Y="425"/>
	<Point X="206" Y="424"/>
	<Point X="207" Y="423"/>
	<Point X="208" Y="422"/>
	<Point X="210" Y="418"/>
	<Point X="216" Y="407"/>
	<Point X="233" Y="381"/>
	<Point X="263" Y="337"/>
	<Point X="295" Y="292"/>
	<Point X="316" Y="261"/>
	<Point X="330" Y="242"/>
	<Point X="340" Y="229"/>
	<Point X="344" Y="224"/>
	<Point X="345" Y="222"/>
</Gesture>
