<?xml version="1.0" ?>
<Gesture User="user3" Gesture="pigtail2" Number="2" NumPts="36" Date="02-03-2023" Time="13:17:07">
	<Point X="210" Y="490"/>
	<Point X="219" Y="484"/>
	<Point X="233" Y="472"/>
	<Point X="248" Y="459"/>
	<Point X="261" Y="449"/>
	<Point X="271" Y="438"/>
	<Point X="276" Y="431"/>
	<Point X="280" Y="423"/>
	<Point X="282" Y="413"/>
	<Point X="283" Y="402"/>
	<Point X="283" Y="393"/>
	<Point X="282" Y="386"/>
	<Point X="280" Y="379"/>
	<Point X="275" Y="375"/>
	<Point X="271" Y="373"/>
	<Point X="265" Y="372"/>
	<Point X="260" Y="372"/>
	<Point X="256" Y="373"/>
	<Point X="253" Y="375"/>
	<Point X="250" Y="378"/>
	<Point X="247" Y="383"/>
	<Point X="244" Y="391"/>
	<Point X="242" Y="402"/>
	<Point X="240" Y="414"/>
	<Point X="239" Y="427"/>
	<Point X="241" Y="438"/>
	<Point X="246" Y="448"/>
	<Point X="256" Y="458"/>
	<Point X="271" Y="470"/>
	<Point X="288" Y="480"/>
	<Point X="304" Y="490"/>
	<Point X="316" Y="496"/>
	<Point X="324" Y="500"/>
	<Point X="330" Y="502"/>
	<Point X="333" Y="503"/>
	<Point X="334" Y="504"/>
</Gesture>
