<?xml version="1.0" ?>
<Gesture User="user2" Gesture="x5" Number="5" NumPts="35" Date="02-03-2023" Time="13:17:07">
	<Point X="168" Y="347"/>
	<Point X="187" Y="353"/>
	<Point X="221" Y="367"/>
	<Point X="264" Y="390"/>
	<Point X="297" Y="413"/>
	<Point X="313" Y="425"/>
	<Point X="320" Y="432"/>
	<Point X="326" Y="437"/>
	<Point X="327" Y="438"/>
	<Point X="327" Y="436"/>
	<Point X="324" Y="426"/>
	<Point X="320" Y="408"/>
	<Point X="319" Y="383"/>
	<Point X="319" Y="359"/>
	<Point X="321" Y="336"/>
	<Point X="325" Y="319"/>
	<Point X="327" Y="309"/>
	<Point X="328" Y="303"/>
	<Point X="329" Y="300"/>
	<Point X="329" Y="299"/>
	<Point X="328" Y="300"/>
	<Point X="328" Y="303"/>
	<Point X="325" Y="308"/>
	<Point X="315" Y="324"/>
	<Point X="293" Y="352"/>
	<Point X="264" Y="388"/>
	<Point X="236" Y="424"/>
	<Point X="216" Y="452"/>
	<Point X="204" Y="472"/>
	<Point X="196" Y="485"/>
	<Point X="192" Y="492"/>
	<Point X="191" Y="496"/>
	<Point X="190" Y="497"/>
	<Point X="189" Y="497"/>
	<Point X="189" Y="495"/>
</Gesture>
