<?xml version="1.0" ?>
<Gesture User="user5" Gesture="check1" Number="1" NumPts="62" Date="28-02-2023" Time="16:12:11">
	<Point X="112" Y="193"/>
	<Point X="116" Y="200"/>
	<Point X="117" Y="202"/>
	<Point X="119" Y="204"/>
	<Point X="120" Y="206"/>
	<Point X="122" Y="209"/>
	<Point X="124" Y="211"/>
	<Point X="126" Y="214"/>
	<Point X="128" Y="216"/>
	<Point X="130" Y="219"/>
	<Point X="132" Y="222"/>
	<Point X="135" Y="224"/>
	<Point X="137" Y="227"/>
	<Point X="139" Y="228"/>
	<Point X="140" Y="230"/>
	<Point X="141" Y="232"/>
	<Point X="143" Y="233"/>
	<Point X="144" Y="234"/>
	<Point X="145" Y="234"/>
	<Point X="145" Y="235"/>
	<Point X="146" Y="235"/>
	<Point X="146" Y="236"/>
	<Point X="147" Y="236"/>
	<Point X="147" Y="237"/>
	<Point X="148" Y="237"/>
	<Point X="148" Y="237"/>
	<Point X="149" Y="237"/>
	<Point X="149" Y="237"/>
	<Point X="150" Y="236"/>
	<Point X="151" Y="236"/>
	<Point X="152" Y="235"/>
	<Point X="154" Y="234"/>
	<Point X="156" Y="231"/>
	<Point X="159" Y="228"/>
	<Point X="162" Y="225"/>
	<Point X="165" Y="221"/>
	<Point X="170" Y="215"/>
	<Point X="176" Y="210"/>
	<Point X="181" Y="203"/>
	<Point X="187" Y="196"/>
	<Point X="194" Y="188"/>
	<Point X="201" Y="179"/>
	<Point X="208" Y="170"/>
	<Point X="216" Y="160"/>
	<Point X="225" Y="151"/>
	<Point X="234" Y="141"/>
	<Point X="243" Y="131"/>
	<Point X="250" Y="123"/>
	<Point X="258" Y="114"/>
	<Point X="265" Y="107"/>
	<Point X="270" Y="101"/>
	<Point X="276" Y="96"/>
	<Point X="280" Y="92"/>
	<Point X="284" Y="88"/>
	<Point X="287" Y="85"/>
	<Point X="289" Y="83"/>
	<Point X="291" Y="81"/>
	<Point X="292" Y="80"/>
	<Point X="293" Y="80"/>
	<Point X="294" Y="79"/>
	<Point X="295" Y="79"/>
	<Point X="295" Y="79"/>
</Gesture>
