<?xml version="1.0" ?>
<Gesture User="user5" Gesture="triangle3" Number="3" NumPts="87" Date="28-02-2023" Time="16:12:11">
	<Point X="155" Y="59"/>
	<Point X="124" Y="90"/>
	<Point X="117" Y="100"/>
	<Point X="110" Y="109"/>
	<Point X="103" Y="120"/>
	<Point X="97" Y="130"/>
	<Point X="92" Y="138"/>
	<Point X="85" Y="148"/>
	<Point X="80" Y="156"/>
	<Point X="76" Y="161"/>
	<Point X="72" Y="167"/>
	<Point X="69" Y="171"/>
	<Point X="66" Y="175"/>
	<Point X="65" Y="178"/>
	<Point X="63" Y="180"/>
	<Point X="62" Y="182"/>
	<Point X="61" Y="183"/>
	<Point X="61" Y="184"/>
	<Point X="60" Y="184"/>
	<Point X="60" Y="185"/>
	<Point X="60" Y="185"/>
	<Point X="60" Y="186"/>
	<Point X="60" Y="186"/>
	<Point X="61" Y="187"/>
	<Point X="63" Y="187"/>
	<Point X="66" Y="188"/>
	<Point X="71" Y="188"/>
	<Point X="78" Y="188"/>
	<Point X="87" Y="187"/>
	<Point X="97" Y="187"/>
	<Point X="108" Y="185"/>
	<Point X="120" Y="184"/>
	<Point X="131" Y="184"/>
	<Point X="144" Y="183"/>
	<Point X="155" Y="182"/>
	<Point X="165" Y="182"/>
	<Point X="176" Y="181"/>
	<Point X="184" Y="181"/>
	<Point X="193" Y="180"/>
	<Point X="202" Y="180"/>
	<Point X="209" Y="180"/>
	<Point X="217" Y="180"/>
	<Point X="223" Y="180"/>
	<Point X="229" Y="180"/>
	<Point X="234" Y="180"/>
	<Point X="237" Y="180"/>
	<Point X="240" Y="180"/>
	<Point X="243" Y="180"/>
	<Point X="245" Y="180"/>
	<Point X="246" Y="180"/>
	<Point X="248" Y="180"/>
	<Point X="249" Y="180"/>
	<Point X="249" Y="180"/>
	<Point X="250" Y="179"/>
	<Point X="250" Y="179"/>
	<Point X="250" Y="178"/>
	<Point X="250" Y="177"/>
	<Point X="250" Y="176"/>
	<Point X="250" Y="173"/>
	<Point X="249" Y="169"/>
	<Point X="246" Y="165"/>
	<Point X="244" Y="159"/>
	<Point X="241" Y="154"/>
	<Point X="236" Y="149"/>
	<Point X="232" Y="143"/>
	<Point X="227" Y="137"/>
	<Point X="222" Y="132"/>
	<Point X="217" Y="126"/>
	<Point X="211" Y="120"/>
	<Point X="206" Y="113"/>
	<Point X="201" Y="107"/>
	<Point X="196" Y="101"/>
	<Point X="192" Y="96"/>
	<Point X="187" Y="90"/>
	<Point X="182" Y="85"/>
	<Point X="178" Y="80"/>
	<Point X="175" Y="76"/>
	<Point X="172" Y="73"/>
	<Point X="169" Y="70"/>
	<Point X="167" Y="67"/>
	<Point X="165" Y="65"/>
	<Point X="164" Y="64"/>
	<Point X="163" Y="62"/>
	<Point X="162" Y="61"/>
	<Point X="161" Y="58"/>
	<Point X="161" Y="57"/>
	<Point X="161" Y="57"/>
</Gesture>
